dvgroup_factory/__init__.py
dvgroup_factory/factory.py
dvgroup_factory/middleware.py
dvgroup_factory/prometheus.py
dvgroup_factory/security.py
dvgroup_factory/etl/__init__.py
dvgroup_factory/etl/copy_utils.py
dvgroup_factory/etl/greenplum_utils.py
dvgroup_factory-0.0.60.dist-info/LICENSE
dvgroup_factory-0.0.60.dist-info/METADATA
dvgroup_factory-0.0.60.dist-info/WHEEL
dvgroup_factory-0.0.60.dist-info/top_level.txt
dvgroup_factory-0.0.60.dist-info/RECORD
