Metadata-Version: 2.1
Name: dvgroup-factory
Version: 0.0.60
Summary: Service factory for DVGroup
Home-page: 
Author: Victor Sh
Author-email: victor.sh@dvgroup.com
License: UNKNOWN
Platform: UNKNOWN
Classifier: Programming Language :: Python :: 3
Classifier: License :: OSI Approved :: MIT License
Classifier: Operating System :: OS Independent
Requires-Python: >=3.6
License-File: LICENSE
Requires-Dist: singleton-decorator
Requires-Dist: hvac
Requires-Dist: consulate
Requires-Dist: clickhouse-driver
Requires-Dist: kafka-python (>=2.0.2)
Requires-Dist: azure-core (>=1.18.0)
Requires-Dist: azure-storage-blob (>=12.9.0)
Requires-Dist: python-logging-loki
Requires-Dist: aiokafka
Requires-Dist: psycopg2-binary
Requires-Dist: python-consul (==1.1.0)
Requires-Dist: aioch (==0.0.2)
Requires-Dist: prometheus-client (==0.12.0)
Requires-Dist: aiohttp
Requires-Dist: aioboto3
Requires-Dist: boto3
Requires-Dist: pyjwt
Requires-Dist: fastapi
Requires-Dist: SQLAlchemy (==1.4.31)
Requires-Dist: redis (>=4.2.0)
Requires-Dist: clickhouse-pool
